{"priceData":{"Wed Jun 30 2021 20:00:00 GMT+0000 (Coordinated Universal Time)":{"Close":10.87,"DownTicks":10377,"DownVolume":2836674,"High":11.37,"Low":10.8,"Open":11.11,"Status":536870917,"TimeStamp":"/Date(1625083200000)/","TotalTicks":19341,"TotalVolume":5452700,"UnchangedTicks":0,"UnchangedVolume":0,"UpTicks":8964,"UpVolume":2616019,"OpenInterest":0},"Mon May 31 2021 20:00:00 GMT+0000 (Coordinated Universal Time)":{"Close":11.11,"DownTicks":9409,"DownVolume":3184817,"High":11.19,"Low":10.46,"Open":10.72,"Status":536870917,"TimeStamp":"/Date(1622491200000)/","TotalTicks":19346,"TotalVolume":6737217,"UnchangedTicks":0,"UnchangedVolume":0,"UpTicks":9937,"UpVolume":3610496,"OpenInterest":0},"Fri Apr 30 2021 20:00:00 GMT+0000 (Coordinated Universal Time)":{"Close":10.36,"DownTicks":941,"DownVolume":372214,"High":10.41,"Low":10.31,"Open":10.38,"Status":536870917,"TimeStamp":"/Date(1619812800000)/","TotalTicks":1896,"TotalVolume":684391,"UnchangedTicks":0,"UnchangedVolume":0,"UpTicks":955,"UpVolume":312175,"OpenInterest":0},"Wed Mar 31 2021 20:00:00 GMT+0000 (Coordinated Universal Time)":{"Close":10.32,"DownTicks":10051,"DownVolume":3698625,"High":10.36,"Low":9.63,"Open":9.73,"Status":29,"TimeStamp":"/Date(1617220800000)/","TotalTicks":20415,"TotalVolume":7387870,"UnchangedTicks":0,"UnchangedVolume":0,"UpTicks":10364,"UpVolume":3689238,"OpenInterest":0},"Fri Feb 26 2021 21:00:00 GMT+0000 (Coordinated Universal Time)":{"Close":9.72,"DownTicks":11198,"DownVolume":3456248,"High":10.07,"Low":9.51,"Open":9.66,"Status":29,"TimeStamp":"/Date(1614373200000)/","TotalTicks":22112,"TotalVolume":6848783,"UnchangedTicks":0,"UnchangedVolume":0,"UpTicks":10914,"UpVolume":3392529,"OpenInterest":0},"Fri Jan 29 2021 21:00:00 GMT+0000 (Coordinated Universal Time)":{"Close":9.61,"DownTicks":10208,"DownVolume":3511541,"High":9.95,"Low":9.29,"Open":9.69,"Status":29,"TimeStamp":"/Date(1611954000000)/","TotalTicks":20291,"TotalVolume":6728078,"UnchangedTicks":0,"UnchangedVolume":0,"UpTicks":10083,"UpVolume":3216527,"OpenInterest":0},"Thu Dec 31 2020 21:00:00 GMT+0000 (Coordinated Universal Time)":{"Close":9.68,"DownTicks":10740,"DownVolume":3657323,"High":9.79,"Low":9.33,"Open":9.5,"Status":29,"TimeStamp":"/Date(1609448400000)/","TotalTicks":21142,"TotalVolume":7179153,"UnchangedTicks":0,"UnchangedVolume":0,"UpTicks":10402,"UpVolume":3521818,"OpenInterest":0},"Mon Nov 30 2020 21:00:00 GMT+0000 (Coordinated Universal Time)":{"Close":9.44,"DownTicks":13065,"DownVolume":4314458,"High":9.57,"Low":8.17,"Open":8.17,"Status":29,"TimeStamp":"/Date(1606770000000)/","TotalTicks":27050,"TotalVolume":8913881,"UnchangedTicks":0,"UnchangedVolume":0,"UpTicks":13985,"UpVolume":4599411,"OpenInterest":0},"Fri Oct 30 2020 20:00:00 GMT+0000 (Coordinated Universal Time)":{"Close":8.13,"DownTicks":10323,"DownVolume":3442265,"High":8.88,"Low":8.06,"Open":8.61,"Status":29,"TimeStamp":"/Date(1604088000000)/","TotalTicks":20600,"TotalVolume":6780458,"UnchangedTicks":0,"UnchangedVolume":0,"UpTicks":10277,"UpVolume":3338183,"OpenInterest":0},"Wed Sep 30 2020 20:00:00 GMT+0000 (Coordinated Universal Time)":{"Close":8.54,"DownTicks":9858,"DownVolume":3164963,"High":9.13,"Low":8.37,"Open":8.98,"Status":29,"TimeStamp":"/Date(1601496000000)/","TotalTicks":19094,"TotalVolume":6233672,"UnchangedTicks":0,"UnchangedVolume":0,"UpTicks":9236,"UpVolume":3068697,"OpenInterest":0},"Mon Aug 31 2020 20:00:00 GMT+0000 (Coordinated Universal Time)":{"Close":9,"DownTicks":6856,"DownVolume":2593149,"High":9.26,"Low":8.81,"Open":8.85,"Status":29,"TimeStamp":"/Date(1598904000000)/","TotalTicks":14304,"TotalVolume":5156255,"UnchangedTicks":0,"UnchangedVolume":0,"UpTicks":7448,"UpVolume":2563095,"OpenInterest":0},"Fri Jul 31 2020 20:00:00 GMT+0000 (Coordinated Universal Time)":{"Close":8.81,"DownTicks":8715,"DownVolume":3186225,"High":8.95,"Low":8.6,"Open":8.65,"Status":29,"TimeStamp":"/Date(1596225600000)/","TotalTicks":17578,"TotalVolume":6039940,"UnchangedTicks":0,"UnchangedVolume":0,"UpTicks":8863,"UpVolume":2853702,"OpenInterest":0},"Tue Jun 30 2020 20:00:00 GMT+0000 (Coordinated Universal Time)":{"Close":8.65,"DownTicks":13625,"DownVolume":4470631,"High":8.74,"Low":8.05,"Open":8.37,"Status":29,"TimeStamp":"/Date(1593547200000)/","TotalTicks":27020,"TotalVolume":8753924,"UnchangedTicks":0,"UnchangedVolume":0,"UpTicks":13395,"UpVolume":4283281,"OpenInterest":0},"Fri May 29 2020 20:00:00 GMT+0000 (Coordinated Universal Time)":{"Close":8.37,"DownTicks":15190,"DownVolume":4506393,"High":8.44,"Low":7.67,"Open":7.92,"Status":29,"TimeStamp":"/Date(1590782400000)/","TotalTicks":30731,"TotalVolume":9175326,"UnchangedTicks":0,"UnchangedVolume":0,"UpTicks":15541,"UpVolume":4668926,"OpenInterest":0},"Thu Apr 30 2020 20:00:00 GMT+0000 (Coordinated Universal Time)":{"Close":8.02,"DownTicks":22412,"DownVolume":5960381,"High":8.23,"Low":6.94,"Open":7.27,"Status":29,"TimeStamp":"/Date(1588276800000)/","TotalTicks":44023,"TotalVolume":11441817,"UnchangedTicks":0,"UnchangedVolume":0,"UpTicks":21611,"UpVolume":5481427,"OpenInterest":0},"Tue Mar 31 2020 20:00:00 GMT+0000 (Coordinated Universal Time)":{"Close":7.46,"DownTicks":31683,"DownVolume":11203849,"High":9.62,"Low":5.49,"Open":8.91,"Status":29,"TimeStamp":"/Date(1585684800000)/","TotalTicks":61961,"TotalVolume":21668009,"UnchangedTicks":0,"UnchangedVolume":0,"UpTicks":30278,"UpVolume":10464150,"OpenInterest":0},"Fri Feb 28 2020 21:00:00 GMT+0000 (Coordinated Universal Time)":{"Close":8.89,"DownTicks":9945,"DownVolume":3732531,"High":10.57,"Low":8.68,"Open":10.35,"Status":29,"TimeStamp":"/Date(1582923600000)/","TotalTicks":19610,"TotalVolume":7149251,"UnchangedTicks":0,"UnchangedVolume":0,"UpTicks":9665,"UpVolume":3416707,"OpenInterest":0},"Fri Jan 31 2020 21:00:00 GMT+0000 (Coordinated Universal Time)":{"Close":10.32,"DownTicks":9285,"DownVolume":2916002,"High":10.6,"Low":10.2,"Open":10.37,"Status":29,"TimeStamp":"/Date(1580504400000)/","TotalTicks":18092,"TotalVolume":5781983,"UnchangedTicks":0,"UnchangedVolume":0,"UpTicks":8807,"UpVolume":2865971,"OpenInterest":0},"Tue Dec 31 2019 21:00:00 GMT+0000 (Coordinated Universal Time)":{"Close":10.37,"DownTicks":8650,"DownVolume":2409849,"High":10.44,"Low":9.97,"Open":10.31,"Status":29,"TimeStamp":"/Date(1577826000000)/","TotalTicks":17599,"TotalVolume":4830947,"UnchangedTicks":0,"UnchangedVolume":0,"UpTicks":8949,"UpVolume":2421088,"OpenInterest":0},"Fri Nov 29 2019 21:00:00 GMT+0000 (Coordinated Universal Time)":{"Close":10.26,"DownTicks":7811,"DownVolume":2461531,"High":10.33,"Low":9.91,"Open":10.17,"Status":29,"TimeStamp":"/Date(1575061200000)/","TotalTicks":15729,"TotalVolume":4932051,"UnchangedTicks":0,"UnchangedVolume":0,"UpTicks":7918,"UpVolume":2470515,"OpenInterest":0},"Thu Oct 31 2019 20:00:00 GMT+0000 (Coordinated Universal Time)":{"Close":10.14,"DownTicks":9839,"DownVolume":3242224,"High":10.27,"Low":9.37,"Open":9.69,"Status":29,"TimeStamp":"/Date(1572552000000)/","TotalTicks":19511,"TotalVolume":6324408,"UnchangedTicks":0,"UnchangedVolume":0,"UpTicks":9672,"UpVolume":3082171,"OpenInterest":0},"Mon Sep 30 2019 20:00:00 GMT+0000 (Coordinated Universal Time)":{"Close":9.66,"DownTicks":7502,"DownVolume":2505617,"High":9.77,"Low":9.36,"Open":9.39,"Status":29,"TimeStamp":"/Date(1569873600000)/","TotalTicks":15033,"TotalVolume":5023396,"UnchangedTicks":0,"UnchangedVolume":0,"UpTicks":7531,"UpVolume":2517771,"OpenInterest":0},"Fri Aug 30 2019 20:00:00 GMT+0000 (Coordinated Universal Time)":{"Close":9.42,"DownTicks":10179,"DownVolume":3322738,"High":9.8,"Low":9.29,"Open":9.74,"Status":29,"TimeStamp":"/Date(1567195200000)/","TotalTicks":20613,"TotalVolume":6573140,"UnchangedTicks":0,"UnchangedVolume":0,"UpTicks":10434,"UpVolume":3250386,"OpenInterest":0},"Wed Jul 31 2019 20:00:00 GMT+0000 (Coordinated Universal Time)":{"Close":9.74,"DownTicks":8861,"DownVolume":2730324,"High":9.9,"Low":9.65,"Open":9.85,"Status":29,"TimeStamp":"/Date(1564603200000)/","TotalTicks":16783,"TotalVolume":5320302,"UnchangedTicks":0,"UnchangedVolume":0,"UpTicks":7922,"UpVolume":2589968,"OpenInterest":0},"Fri Jun 28 2019 20:00:00 GMT+0000 (Coordinated Universal Time)":{"Close":9.79,"DownTicks":7357,"DownVolume":2360621,"High":9.8,"Low":9.29,"Open":9.41,"Status":29,"TimeStamp":"/Date(1561752000000)/","TotalTicks":14743,"TotalVolume":4766781,"UnchangedTicks":0,"UnchangedVolume":0,"UpTicks":7386,"UpVolume":2406150,"OpenInterest":0},"Fri May 31 2019 20:00:00 GMT+0000 (Coordinated Universal Time)":{"Close":9.43,"DownTicks":9972,"DownVolume":3208464,"High":10.06,"Low":9.41,"Open":9.99,"Status":29,"TimeStamp":"/Date(1559332800000)/","TotalTicks":19928,"TotalVolume":6319613,"UnchangedTicks":0,"UnchangedVolume":0,"UpTicks":9956,"UpVolume":3111138,"OpenInterest":0},"Tue Apr 30 2019 20:00:00 GMT+0000 (Coordinated Universal Time)":{"Close":9.95,"DownTicks":7961,"DownVolume":2842501,"High":10.07,"Low":9.77,"Open":9.82,"Status":29,"TimeStamp":"/Date(1556654400000)/","TotalTicks":16194,"TotalVolume":5865865,"UnchangedTicks":0,"UnchangedVolume":0,"UpTicks":8233,"UpVolume":3023349,"OpenInterest":0},"Fri Mar 29 2019 20:00:00 GMT+0000 (Coordinated Universal Time)":{"Close":9.77,"DownTicks":9707,"DownVolume":3492856,"High":9.94,"Low":9.54,"Open":9.73,"Status":29,"TimeStamp":"/Date(1553889600000)/","TotalTicks":19523,"TotalVolume":7036790,"UnchangedTicks":0,"UnchangedVolume":0,"UpTicks":9816,"UpVolume":3543923,"OpenInterest":0},"Thu Feb 28 2019 21:00:00 GMT+0000 (Coordinated Universal Time)":{"Close":9.69,"DownTicks":10556,"DownVolume":3835529,"High":9.88,"Low":9.58,"Open":9.81,"Status":29,"TimeStamp":"/Date(1551387600000)/","TotalTicks":20467,"TotalVolume":7481535,"UnchangedTicks":0,"UnchangedVolume":0,"UpTicks":9911,"UpVolume":3645997,"OpenInterest":0},"Thu Jan 31 2019 21:00:00 GMT+0000 (Coordinated Universal Time)":{"Close":9.82,"DownTicks":11983,"DownVolume":3873215,"High":10,"Low":9.13,"Open":9.36,"Status":29,"TimeStamp":"/Date(1548968400000)/","TotalTicks":23224,"TotalVolume":7713421,"UnchangedTicks":0,"UnchangedVolume":0,"UpTicks":11241,"UpVolume":3840199,"OpenInterest":0},"Mon Dec 31 2018 21:00:00 GMT+0000 (Coordinated Universal Time)":{"Close":9.53,"DownTicks":17383,"DownVolume":5598692,"High":11,"Low":8.6,"Open":10.96,"Status":29,"TimeStamp":"/Date(1546290000000)/","TotalTicks":33817,"TotalVolume":10590775,"UnchangedTicks":0,"UnchangedVolume":0,"UpTicks":16434,"UpVolume":4992073,"OpenInterest":0},"Fri Nov 30 2018 21:00:00 GMT+0000 (Coordinated Universal Time)":{"Close":10.78,"DownTicks":8312,"DownVolume":2582065,"High":11.34,"Low":10.22,"Open":10.87,"Status":29,"TimeStamp":"/Date(1543611600000)/","TotalTicks":16454,"TotalVolume":5014374,"UnchangedTicks":0,"UnchangedVolume":0,"UpTicks":8142,"UpVolume":2432297,"OpenInterest":0},"Wed Oct 31 2018 20:00:00 GMT+0000 (Coordinated Universal Time)":{"Close":10.83,"DownTicks":11192,"DownVolume":3680784,"High":12.14,"Low":10.42,"Open":12.09,"Status":29,"TimeStamp":"/Date(1541016000000)/","TotalTicks":21812,"TotalVolume":7359503,"UnchangedTicks":0,"UnchangedVolume":0,"UpTicks":10620,"UpVolume":3678707,"OpenInterest":0},"Fri Sep 28 2018 20:00:00 GMT+0000 (Coordinated Universal Time)":{"Close":12.03,"DownTicks":6515,"DownVolume":1916929,"High":12.08,"Low":11.77,"Open":12.01,"Status":29,"TimeStamp":"/Date(1538164800000)/","TotalTicks":13097,"TotalVolume":3919649,"UnchangedTicks":0,"UnchangedVolume":0,"UpTicks":6582,"UpVolume":2002714,"OpenInterest":0},"Fri Aug 31 2018 20:00:00 GMT+0000 (Coordinated Universal Time)":{"Close":12.02,"DownTicks":7307,"DownVolume":2458756,"High":12.38,"Low":11.94,"Open":12.01,"Status":29,"TimeStamp":"/Date(1535745600000)/","TotalTicks":14801,"TotalVolume":4913175,"UnchangedTicks":0,"UnchangedVolume":0,"UpTicks":7494,"UpVolume":2454408,"OpenInterest":0},"Tue Jul 31 2018 20:00:00 GMT+0000 (Coordinated Universal Time)":{"Close":11.99,"DownTicks":6965,"DownVolume":2169272,"High":12.04,"Low":11.72,"Open":11.72,"Status":29,"TimeStamp":"/Date(1533067200000)/","TotalTicks":13308,"TotalVolume":4338712,"UnchangedTicks":0,"UnchangedVolume":0,"UpTicks":6343,"UpVolume":2169429,"OpenInterest":0},"Fri Jun 29 2018 20:00:00 GMT+0000 (Coordinated Universal Time)":{"Close":11.8,"DownTicks":6693,"DownVolume":2111591,"High":12.15,"Low":11.6,"Open":11.6,"Status":29,"TimeStamp":"/Date(1530302400000)/","TotalTicks":13499,"TotalVolume":4303086,"UnchangedTicks":0,"UnchangedVolume":0,"UpTicks":6806,"UpVolume":2191486,"OpenInterest":0},"Thu May 31 2018 20:00:00 GMT+0000 (Coordinated Universal Time)":{"Close":11.6,"DownTicks":6800,"DownVolume":2038752,"High":11.9,"Low":11.4,"Open":11.6,"Status":29,"TimeStamp":"/Date(1527796800000)/","TotalTicks":13623,"TotalVolume":4227417,"UnchangedTicks":0,"UnchangedVolume":0,"UpTicks":6823,"UpVolume":2188653,"OpenInterest":0},"Mon Apr 30 2018 20:00:00 GMT+0000 (Coordinated Universal Time)":{"Close":11.61,"DownTicks":9598,"DownVolume":2680732,"High":11.93,"Low":11.32,"Open":11.52,"Status":29,"TimeStamp":"/Date(1525118400000)/","TotalTicks":18407,"TotalVolume":5135984,"UnchangedTicks":0,"UnchangedVolume":0,"UpTicks":8809,"UpVolume":2455243,"OpenInterest":0},"Fri Mar 30 2018 20:00:00 GMT+0000 (Coordinated Universal Time)":{"Close":11.55,"DownTicks":8820,"DownVolume":2759262,"High":12.08,"Low":11.35,"Open":11.76,"Status":13,"TimeStamp":"/Date(1522440000000)/","TotalTicks":17292,"TotalVolume":5494779,"UnchangedTicks":0,"UnchangedVolume":0,"UpTicks":8472,"UpVolume":2735505,"OpenInterest":0},"Wed Feb 28 2018 21:00:00 GMT+0000 (Coordinated Universal Time)":{"Close":11.76,"DownTicks":12999,"DownVolume":4446065,"High":12.31,"Low":11.15,"Open":12.26,"Status":29,"TimeStamp":"/Date(1519851600000)/","TotalTicks":25277,"TotalVolume":8555269,"UnchangedTicks":0,"UnchangedVolume":0,"UpTicks":12278,"UpVolume":4109191,"OpenInterest":0},"Wed Jan 31 2018 21:00:00 GMT+0000 (Coordinated Universal Time)":{"Close":12.3,"DownTicks":8936,"DownVolume":3368313,"High":12.74,"Low":11.95,"Open":11.98,"Status":29,"TimeStamp":"/Date(1517432400000)/","TotalTicks":17920,"TotalVolume":6747337,"UnchangedTicks":0,"UnchangedVolume":0,"UpTicks":8984,"UpVolume":3379015,"OpenInterest":0},"Fri Dec 29 2017 21:00:00 GMT+0000 (Coordinated Universal Time)":{"Close":11.92,"DownTicks":7131,"DownVolume":2326873,"High":12.05,"Low":11.68,"Open":11.79,"Status":29,"TimeStamp":"/Date(1514581200000)/","TotalTicks":13708,"TotalVolume":4660429,"UnchangedTicks":0,"UnchangedVolume":0,"UpTicks":6577,"UpVolume":2333547,"OpenInterest":0},"Thu Nov 30 2017 21:00:00 GMT+0000 (Coordinated Universal Time)":{"Close":11.82,"DownTicks":6860,"DownVolume":2341668,"High":11.91,"Low":11.55,"Open":11.86,"Status":29,"TimeStamp":"/Date(1512075600000)/","TotalTicks":13843,"TotalVolume":4836914,"UnchangedTicks":0,"UnchangedVolume":0,"UpTicks":6983,"UpVolume":2495232,"OpenInterest":0},"Tue Oct 31 2017 20:00:00 GMT+0000 (Coordinated Universal Time)":{"Close":11.82,"DownTicks":7408,"DownVolume":2627035,"High":11.95,"Low":11.67,"Open":11.86,"Status":29,"TimeStamp":"/Date(1509480000000)/","TotalTicks":14268,"TotalVolume":5114769,"UnchangedTicks":0,"UnchangedVolume":0,"UpTicks":6860,"UpVolume":2487729,"OpenInterest":0},"Fri Sep 29 2017 20:00:00 GMT+0000 (Coordinated Universal Time)":{"Close":11.84,"DownTicks":6136,"DownVolume":2391586,"High":11.98,"Low":11.6,"Open":11.74,"Status":29,"TimeStamp":"/Date(1506715200000)/","TotalTicks":12254,"TotalVolume":4583074,"UnchangedTicks":0,"UnchangedVolume":0,"UpTicks":6118,"UpVolume":2191477,"OpenInterest":0},"Thu Aug 31 2017 20:00:00 GMT+0000 (Coordinated Universal Time)":{"Close":11.73,"DownTicks":9654,"DownVolume":3457845,"High":11.9,"Low":11.24,"Open":11.83,"Status":29,"TimeStamp":"/Date(1504209600000)/","TotalTicks":19299,"TotalVolume":6893893,"UnchangedTicks":0,"UnchangedVolume":0,"UpTicks":9645,"UpVolume":3436036,"OpenInterest":0},"Mon Jul 31 2017 20:00:00 GMT+0000 (Coordinated Universal Time)":{"Close":11.8,"DownTicks":7291,"DownVolume":2801300,"High":11.9,"Low":11.28,"Open":11.44,"Status":29,"TimeStamp":"/Date(1501531200000)/","TotalTicks":14527,"TotalVolume":5846461,"UnchangedTicks":0,"UnchangedVolume":0,"UpTicks":7236,"UpVolume":3045148,"OpenInterest":0},"Fri Jun 30 2017 20:00:00 GMT+0000 (Coordinated Universal Time)":{"Close":11.38,"DownTicks":10175,"DownVolume":3731180,"High":11.67,"Low":11.31,"Open":11.56,"Status":29,"TimeStamp":"/Date(1498852800000)/","TotalTicks":19888,"TotalVolume":7303102,"UnchangedTicks":0,"UnchangedVolume":0,"UpTicks":9713,"UpVolume":3571913,"OpenInterest":0}},"rsiData":{"Wed Jun 30 2021 20:00:00 GMT+0000 (Coordinated Universal Time)":60.45,"Mon May 31 2021 20:00:00 GMT+0000 (Coordinated Universal Time)":63.22,"Fri Apr 30 2021 20:00:00 GMT+0000 (Coordinated Universal Time)":57.57,"Wed Mar 31 2021 20:00:00 GMT+0000 (Coordinated Universal Time)":57.24,"Fri Feb 26 2021 21:00:00 GMT+0000 (Coordinated Universal Time)":52.17,"Fri Jan 29 2021 21:00:00 GMT+0000 (Coordinated Universal Time)":51.18,"Thu Dec 31 2020 21:00:00 GMT+0000 (Coordinated Universal Time)":51.81,"Mon Nov 30 2020 21:00:00 GMT+0000 (Coordinated Universal Time)":49.84,"Fri Oct 30 2020 20:00:00 GMT+0000 (Coordinated Universal Time)":36.71,"Wed Sep 30 2020 20:00:00 GMT+0000 (Coordinated Universal Time)":39.73,"Mon Aug 31 2020 20:00:00 GMT+0000 (Coordinated Universal Time)":43.46,"Fri Jul 31 2020 20:00:00 GMT+0000 (Coordinated Universal Time)":41.35,"Tue Jun 30 2020 20:00:00 GMT+0000 (Coordinated Universal Time)":39.58,"Fri May 29 2020 20:00:00 GMT+0000 (Coordinated Universal Time)":36.48,"Thu Apr 30 2020 20:00:00 GMT+0000 (Coordinated Universal Time)":32.46,"Tue Mar 31 2020 20:00:00 GMT+0000 (Coordinated Universal Time)":25.43,"Fri Feb 28 2020 21:00:00 GMT+0000 (Coordinated Universal Time)":33.75,"Fri Jan 31 2020 21:00:00 GMT+0000 (Coordinated Universal Time)":48.49,"Tue Dec 31 2019 21:00:00 GMT+0000 (Coordinated Universal Time)":49.18,"Fri Nov 29 2019 21:00:00 GMT+0000 (Coordinated Universal Time)":47.65,"Thu Oct 31 2019 20:00:00 GMT+0000 (Coordinated Universal Time)":45.99,"Mon Sep 30 2019 20:00:00 GMT+0000 (Coordinated Universal Time)":38.81,"Fri Aug 30 2019 20:00:00 GMT+0000 (Coordinated Universal Time)":34.78,"Wed Jul 31 2019 20:00:00 GMT+0000 (Coordinated Universal Time)":37.86,"Fri Jun 28 2019 20:00:00 GMT+0000 (Coordinated Universal Time)":38.36,"Fri May 31 2019 20:00:00 GMT+0000 (Coordinated Universal Time)":32.47,"Tue Apr 30 2019 20:00:00 GMT+0000 (Coordinated Universal Time)":37.24,"Fri Mar 29 2019 20:00:00 GMT+0000 (Coordinated Universal Time)":34.13,"Thu Feb 28 2019 21:00:00 GMT+0000 (Coordinated Universal Time)":32.75,"Thu Jan 31 2019 21:00:00 GMT+0000 (Coordinated Universal Time)":33.82,"Mon Dec 31 2018 21:00:00 GMT+0000 (Coordinated Universal Time)":29.03,"Fri Nov 30 2018 21:00:00 GMT+0000 (Coordinated Universal Time)":40.85,"Wed Oct 31 2018 20:00:00 GMT+0000 (Coordinated Universal Time)":41.48,"Fri Sep 28 2018 20:00:00 GMT+0000 (Coordinated Universal Time)":63.07,"Fri Aug 31 2018 20:00:00 GMT+0000 (Coordinated Universal Time)":62.92,"Tue Jul 31 2018 20:00:00 GMT+0000 (Coordinated Universal Time)":62.5,"Fri Jun 29 2018 20:00:00 GMT+0000 (Coordinated Universal Time)":59.81,"Thu May 31 2018 20:00:00 GMT+0000 (Coordinated Universal Time)":56.77,"Mon Apr 30 2018 20:00:00 GMT+0000 (Coordinated Universal Time)":56.97,"Fri Mar 30 2018 20:00:00 GMT+0000 (Coordinated Universal Time)":56.11,"Wed Feb 28 2018 21:00:00 GMT+0000 (Coordinated Universal Time)":60.01,"Wed Jan 31 2018 21:00:00 GMT+0000 (Coordinated Universal Time)":71.95,"Fri Dec 29 2017 21:00:00 GMT+0000 (Coordinated Universal Time)":67.75,"Thu Nov 30 2017 21:00:00 GMT+0000 (Coordinated Universal Time)":66.53,"Tue Oct 31 2017 20:00:00 GMT+0000 (Coordinated Universal Time)":66.53,"Fri Sep 29 2017 20:00:00 GMT+0000 (Coordinated Universal Time)":66.97,"Thu Aug 31 2017 20:00:00 GMT+0000 (Coordinated Universal Time)":65.82,"Mon Jul 31 2017 20:00:00 GMT+0000 (Coordinated Universal Time)":67.2,"Fri Jun 30 2017 20:00:00 GMT+0000 (Coordinated Universal Time)":62.87}}