{"priceData":{"Wed Jun 30 2021 20:00:00 GMT+0000 (Coordinated Universal Time)":{"Close":14.38,"DownTicks":68969,"DownVolume":9430227,"High":15.31,"Low":14.29,"Open":15.19,"Status":536870917,"TimeStamp":"/Date(1625083200000)/","TotalTicks":132930,"TotalVolume":17664084,"UnchangedTicks":0,"UnchangedVolume":0,"UpTicks":63961,"UpVolume":8233845,"OpenInterest":0},"Mon May 31 2021 20:00:00 GMT+0000 (Coordinated Universal Time)":{"Close":15.15,"DownTicks":75152,"DownVolume":9628292,"High":15.36,"Low":14.51,"Open":15.01,"Status":536870917,"TimeStamp":"/Date(1622491200000)/","TotalTicks":148893,"TotalVolume":18852559,"UnchangedTicks":0,"UnchangedVolume":0,"UpTicks":73741,"UpVolume":9224258,"OpenInterest":0},"Fri Apr 30 2021 20:00:00 GMT+0000 (Coordinated Universal Time)":{"Close":15.09,"DownTicks":12957,"DownVolume":1538619,"High":15.25,"Low":14.51,"Open":14.51,"Status":536870917,"TimeStamp":"/Date(1619812800000)/","TotalTicks":27271,"TotalVolume":3518912,"UnchangedTicks":0,"UnchangedVolume":0,"UpTicks":14314,"UpVolume":1980292,"OpenInterest":0},"Wed Mar 31 2021 20:00:00 GMT+0000 (Coordinated Universal Time)":{"Close":14.5,"DownTicks":108489,"DownVolume":15779593,"High":14.78,"Low":13.91,"Open":14.33,"Status":29,"TimeStamp":"/Date(1617220800000)/","TotalTicks":215504,"TotalVolume":29882503,"UnchangedTicks":0,"UnchangedVolume":0,"UpTicks":107015,"UpVolume":14102895,"OpenInterest":0},"Fri Feb 26 2021 21:00:00 GMT+0000 (Coordinated Universal Time)":{"Close":14.12,"DownTicks":79805,"DownVolume":9337865,"High":14.95,"Low":13.33,"Open":13.5,"Status":29,"TimeStamp":"/Date(1614373200000)/","TotalTicks":159207,"TotalVolume":18522586,"UnchangedTicks":0,"UnchangedVolume":0,"UpTicks":79402,"UpVolume":9184712,"OpenInterest":0},"Fri Jan 29 2021 21:00:00 GMT+0000 (Coordinated Universal Time)":{"Close":13.41,"DownTicks":81911,"DownVolume":9772248,"High":14.55,"Low":13.4,"Open":13.92,"Status":29,"TimeStamp":"/Date(1611954000000)/","TotalTicks":162655,"TotalVolume":18382377,"UnchangedTicks":0,"UnchangedVolume":0,"UpTicks":80744,"UpVolume":8610117,"OpenInterest":0},"Thu Dec 31 2020 21:00:00 GMT+0000 (Coordinated Universal Time)":{"Close":13.8,"DownTicks":110046,"DownVolume":14502177,"High":14,"Low":13.05,"Open":13.31,"Status":29,"TimeStamp":"/Date(1609448400000)/","TotalTicks":220161,"TotalVolume":28855901,"UnchangedTicks":0,"UnchangedVolume":0,"UpTicks":110115,"UpVolume":14353717,"OpenInterest":0},"Mon Nov 30 2020 21:00:00 GMT+0000 (Coordinated Universal Time)":{"Close":13.06,"DownTicks":137694,"DownVolume":18003382,"High":13.41,"Low":11.55,"Open":11.96,"Status":29,"TimeStamp":"/Date(1606770000000)/","TotalTicks":272666,"TotalVolume":33550997,"UnchangedTicks":0,"UnchangedVolume":0,"UpTicks":134972,"UpVolume":15547604,"OpenInterest":0},"Fri Oct 30 2020 20:00:00 GMT+0000 (Coordinated Universal Time)":{"Close":11.87,"DownTicks":128500,"DownVolume":16138880,"High":12.83,"Low":11.2,"Open":11.51,"Status":29,"TimeStamp":"/Date(1604088000000)/","TotalTicks":252205,"TotalVolume":29666242,"UnchangedTicks":0,"UnchangedVolume":0,"UpTicks":123705,"UpVolume":13527352,"OpenInterest":0},"Wed Sep 30 2020 20:00:00 GMT+0000 (Coordinated Universal Time)":{"Close":11.41,"DownTicks":128402,"DownVolume":14697943,"High":11.95,"Low":10.54,"Open":11.49,"Status":29,"TimeStamp":"/Date(1601496000000)/","TotalTicks":256911,"TotalVolume":28422585,"UnchangedTicks":0,"UnchangedVolume":0,"UpTicks":128509,"UpVolume":13724631,"OpenInterest":0},"Mon Aug 31 2020 20:00:00 GMT+0000 (Coordinated Universal Time)":{"Close":11.46,"DownTicks":87623,"DownVolume":12192348,"High":12.65,"Low":11.17,"Open":12.37,"Status":29,"TimeStamp":"/Date(1598904000000)/","TotalTicks":173750,"TotalVolume":24246853,"UnchangedTicks":0,"UnchangedVolume":0,"UpTicks":86127,"UpVolume":12054493,"OpenInterest":0},"Fri Jul 31 2020 20:00:00 GMT+0000 (Coordinated Universal Time)":{"Close":12.31,"DownTicks":98093,"DownVolume":14096911,"High":12.75,"Low":11.22,"Open":11.87,"Status":29,"TimeStamp":"/Date(1596225600000)/","TotalTicks":197536,"TotalVolume":26749307,"UnchangedTicks":0,"UnchangedVolume":0,"UpTicks":99443,"UpVolume":12652384,"OpenInterest":0},"Tue Jun 30 2020 20:00:00 GMT+0000 (Coordinated Universal Time)":{"Close":11.86,"DownTicks":93438,"DownVolume":10511609,"High":12.6,"Low":10.72,"Open":11.59,"Status":29,"TimeStamp":"/Date(1593547200000)/","TotalTicks":185078,"TotalVolume":20644473,"UnchangedTicks":0,"UnchangedVolume":0,"UpTicks":91640,"UpVolume":10132851,"OpenInterest":0},"Fri May 29 2020 20:00:00 GMT+0000 (Coordinated Universal Time)":{"Close":11.57,"DownTicks":84401,"DownVolume":11676963,"High":12.21,"Low":10.08,"Open":11.19,"Status":29,"TimeStamp":"/Date(1590782400000)/","TotalTicks":169322,"TotalVolume":24922182,"UnchangedTicks":0,"UnchangedVolume":0,"UpTicks":84921,"UpVolume":13245213,"OpenInterest":0},"Thu Apr 30 2020 20:00:00 GMT+0000 (Coordinated Universal Time)":{"Close":11.59,"DownTicks":110893,"DownVolume":12476112,"High":11.91,"Low":9.09,"Open":9.82,"Status":29,"TimeStamp":"/Date(1588276800000)/","TotalTicks":221862,"TotalVolume":26744658,"UnchangedTicks":0,"UnchangedVolume":0,"UpTicks":110969,"UpVolume":14268533,"OpenInterest":0},"Tue Mar 31 2020 20:00:00 GMT+0000 (Coordinated Universal Time)":{"Close":10.34,"DownTicks":137947,"DownVolume":16791157,"High":13.55,"Low":8.06,"Open":13.07,"Status":29,"TimeStamp":"/Date(1585684800000)/","TotalTicks":278612,"TotalVolume":35913040,"UnchangedTicks":0,"UnchangedVolume":0,"UpTicks":140665,"UpVolume":19121871,"OpenInterest":0},"Fri Feb 28 2020 21:00:00 GMT+0000 (Coordinated Universal Time)":{"Close":12.99,"DownTicks":95280,"DownVolume":12962402,"High":16.25,"Low":12.27,"Open":14.52,"Status":29,"TimeStamp":"/Date(1582923600000)/","TotalTicks":193105,"TotalVolume":26063193,"UnchangedTicks":0,"UnchangedVolume":0,"UpTicks":97825,"UpVolume":13100781,"OpenInterest":0},"Fri Jan 31 2020 21:00:00 GMT+0000 (Coordinated Universal Time)":{"Close":14.39,"DownTicks":66958,"DownVolume":11699791,"High":16.18,"Low":14.22,"Open":15.26,"Status":29,"TimeStamp":"/Date(1580504400000)/","TotalTicks":131784,"TotalVolume":22891803,"UnchangedTicks":0,"UnchangedVolume":0,"UpTicks":64826,"UpVolume":11314870,"OpenInterest":0},"Tue Dec 31 2019 21:00:00 GMT+0000 (Coordinated Universal Time)":{"Close":15.05,"DownTicks":70854,"DownVolume":12071832,"High":15.28,"Low":12.98,"Open":13.39,"Status":29,"TimeStamp":"/Date(1577826000000)/","TotalTicks":138328,"TotalVolume":25354316,"UnchangedTicks":0,"UnchangedVolume":0,"UpTicks":67474,"UpVolume":13282473,"OpenInterest":0},"Fri Nov 29 2019 21:00:00 GMT+0000 (Coordinated Universal Time)":{"Close":13.41,"DownTicks":55930,"DownVolume":7279089,"High":13.71,"Low":11.65,"Open":11.71,"Status":29,"TimeStamp":"/Date(1575061200000)/","TotalTicks":112548,"TotalVolume":13819695,"UnchangedTicks":0,"UnchangedVolume":0,"UpTicks":56618,"UpVolume":6540597,"OpenInterest":0},"Thu Oct 31 2019 20:00:00 GMT+0000 (Coordinated Universal Time)":{"Close":11.71,"DownTicks":76784,"DownVolume":8183761,"High":13.23,"Low":11.25,"Open":12.28,"Status":29,"TimeStamp":"/Date(1572552000000)/","TotalTicks":154025,"TotalVolume":17684222,"UnchangedTicks":0,"UnchangedVolume":0,"UpTicks":77241,"UpVolume":9500447,"OpenInterest":0},"Mon Sep 30 2019 20:00:00 GMT+0000 (Coordinated Universal Time)":{"Close":12.2,"DownTicks":76857,"DownVolume":8830935,"High":12.63,"Low":10.27,"Open":10.52,"Status":29,"TimeStamp":"/Date(1569873600000)/","TotalTicks":154117,"TotalVolume":19991394,"UnchangedTicks":0,"UnchangedVolume":0,"UpTicks":77260,"UpVolume":11160446,"OpenInterest":0},"Fri Aug 30 2019 20:00:00 GMT+0000 (Coordinated Universal Time)":{"Close":10.66,"DownTicks":97651,"DownVolume":13691255,"High":12.23,"Low":9.65,"Open":11.85,"Status":29,"TimeStamp":"/Date(1567195200000)/","TotalTicks":194018,"TotalVolume":27205488,"UnchangedTicks":0,"UnchangedVolume":0,"UpTicks":96367,"UpVolume":13514222,"OpenInterest":0},"Wed Jul 31 2019 20:00:00 GMT+0000 (Coordinated Universal Time)":{"Close":10.46,"DownTicks":77881,"DownVolume":11824918,"High":10.61,"Low":9.18,"Open":10.46,"Status":29,"TimeStamp":"/Date(1564603200000)/","TotalTicks":153360,"TotalVolume":23974456,"UnchangedTicks":0,"UnchangedVolume":0,"UpTicks":75479,"UpVolume":12149531,"OpenInterest":0},"Fri Jun 28 2019 20:00:00 GMT+0000 (Coordinated Universal Time)":{"Close":10.2,"DownTicks":67292,"DownVolume":10025239,"High":10.31,"Low":8.49,"Open":8.49,"Status":29,"TimeStamp":"/Date(1561752000000)/","TotalTicks":134458,"TotalVolume":21470230,"UnchangedTicks":0,"UnchangedVolume":0,"UpTicks":67166,"UpVolume":11444983,"OpenInterest":0},"Fri May 31 2019 20:00:00 GMT+0000 (Coordinated Universal Time)":{"Close":8.53,"DownTicks":93453,"DownVolume":15533658,"High":13.44,"Low":8.51,"Open":13.37,"Status":29,"TimeStamp":"/Date(1559332800000)/","TotalTicks":187792,"TotalVolume":29041161,"UnchangedTicks":0,"UnchangedVolume":0,"UpTicks":94339,"UpVolume":13507491,"OpenInterest":0},"Tue Apr 30 2019 20:00:00 GMT+0000 (Coordinated Universal Time)":{"Close":13.24,"DownTicks":53713,"DownVolume":9677690,"High":13.92,"Low":11.81,"Open":11.84,"Status":29,"TimeStamp":"/Date(1556654400000)/","TotalTicks":107298,"TotalVolume":19053075,"UnchangedTicks":0,"UnchangedVolume":0,"UpTicks":53585,"UpVolume":9375371,"OpenInterest":0},"Fri Mar 29 2019 20:00:00 GMT+0000 (Coordinated Universal Time)":{"Close":11.73,"DownTicks":62213,"DownVolume":8927898,"High":12.6,"Low":11.09,"Open":12.35,"Status":29,"TimeStamp":"/Date(1553889600000)/","TotalTicks":124596,"TotalVolume":18660542,"UnchangedTicks":0,"UnchangedVolume":0,"UpTicks":62383,"UpVolume":9732633,"OpenInterest":0},"Thu Feb 28 2019 21:00:00 GMT+0000 (Coordinated Universal Time)":{"Close":12.12,"DownTicks":67804,"DownVolume":10278482,"High":12.72,"Low":11.04,"Open":11.49,"Status":29,"TimeStamp":"/Date(1551387600000)/","TotalTicks":138268,"TotalVolume":21144013,"UnchangedTicks":0,"UnchangedVolume":0,"UpTicks":70464,"UpVolume":10865523,"OpenInterest":0},"Thu Jan 31 2019 21:00:00 GMT+0000 (Coordinated Universal Time)":{"Close":11.48,"DownTicks":66498,"DownVolume":9351710,"High":11.6,"Low":9.01,"Open":9.56,"Status":29,"TimeStamp":"/Date(1548968400000)/","TotalTicks":133828,"TotalVolume":18807965,"UnchangedTicks":0,"UnchangedVolume":0,"UpTicks":67330,"UpVolume":9456242,"OpenInterest":0},"Mon Dec 31 2018 21:00:00 GMT+0000 (Coordinated Universal Time)":{"Close":9.73,"DownTicks":64464,"DownVolume":9486214,"High":12.13,"Low":8.97,"Open":12.12,"Status":29,"TimeStamp":"/Date(1546290000000)/","TotalTicks":128298,"TotalVolume":21797301,"UnchangedTicks":0,"UnchangedVolume":0,"UpTicks":63834,"UpVolume":12311080,"OpenInterest":0},"Fri Nov 30 2018 21:00:00 GMT+0000 (Coordinated Universal Time)":{"Close":11.89,"DownTicks":71739,"DownVolume":10337462,"High":13.15,"Low":11.4,"Open":11.72,"Status":29,"TimeStamp":"/Date(1543611600000)/","TotalTicks":144272,"TotalVolume":20846313,"UnchangedTicks":0,"UnchangedVolume":0,"UpTicks":72533,"UpVolume":10508839,"OpenInterest":0},"Wed Oct 31 2018 20:00:00 GMT+0000 (Coordinated Universal Time)":{"Close":11.7,"DownTicks":99267,"DownVolume":14753245,"High":15.98,"Low":11.24,"Open":15.98,"Status":29,"TimeStamp":"/Date(1541016000000)/","TotalTicks":200779,"TotalVolume":29488517,"UnchangedTicks":0,"UnchangedVolume":0,"UpTicks":101512,"UpVolume":14735258,"OpenInterest":0},"Fri Sep 28 2018 20:00:00 GMT+0000 (Coordinated Universal Time)":{"Close":15.91,"DownTicks":51585,"DownVolume":6633991,"High":18.62,"Low":15.85,"Open":18.62,"Status":29,"TimeStamp":"/Date(1538164800000)/","TotalTicks":104094,"TotalVolume":13658855,"UnchangedTicks":0,"UnchangedVolume":0,"UpTicks":52509,"UpVolume":7024853,"OpenInterest":0},"Fri Aug 31 2018 20:00:00 GMT+0000 (Coordinated Universal Time)":{"Close":18.7,"DownTicks":70003,"DownVolume":7819199,"High":19.91,"Low":17.02,"Open":17.35,"Status":29,"TimeStamp":"/Date(1535745600000)/","TotalTicks":143708,"TotalVolume":17572550,"UnchangedTicks":0,"UnchangedVolume":0,"UpTicks":73705,"UpVolume":9753337,"OpenInterest":0},"Tue Jul 31 2018 20:00:00 GMT+0000 (Coordinated Universal Time)":{"Close":17.36,"DownTicks":48002,"DownVolume":5936281,"High":18.62,"Low":17.06,"Open":17.57,"Status":29,"TimeStamp":"/Date(1533067200000)/","TotalTicks":96774,"TotalVolume":11901907,"UnchangedTicks":0,"UnchangedVolume":0,"UpTicks":48772,"UpVolume":5965615,"OpenInterest":0},"Fri Jun 29 2018 20:00:00 GMT+0000 (Coordinated Universal Time)":{"Close":17.63,"DownTicks":70525,"DownVolume":11214691,"High":19.62,"Low":17.41,"Open":18.05,"Status":29,"TimeStamp":"/Date(1530302400000)/","TotalTicks":141719,"TotalVolume":21317812,"UnchangedTicks":0,"UnchangedVolume":0,"UpTicks":71194,"UpVolume":10103106,"OpenInterest":0},"Thu May 31 2018 20:00:00 GMT+0000 (Coordinated Universal Time)":{"Close":18.03,"DownTicks":84727,"DownVolume":12250570,"High":18.03,"Low":13.72,"Open":13.88,"Status":29,"TimeStamp":"/Date(1527796800000)/","TotalTicks":169123,"TotalVolume":24975904,"UnchangedTicks":0,"UnchangedVolume":0,"UpTicks":84396,"UpVolume":12725321,"OpenInterest":0},"Mon Apr 30 2018 20:00:00 GMT+0000 (Coordinated Universal Time)":{"Close":13.94,"DownTicks":53908,"DownVolume":6668195,"High":15.99,"Low":13.94,"Open":15.27,"Status":29,"TimeStamp":"/Date(1525118400000)/","TotalTicks":106576,"TotalVolume":13282413,"UnchangedTicks":0,"UnchangedVolume":0,"UpTicks":52668,"UpVolume":6614208,"OpenInterest":0},"Fri Mar 30 2018 20:00:00 GMT+0000 (Coordinated Universal Time)":{"Close":15.29,"DownTicks":51735,"DownVolume":6963698,"High":17.27,"Low":14.69,"Open":16.22,"Status":13,"TimeStamp":"/Date(1522440000000)/","TotalTicks":102783,"TotalVolume":14232777,"UnchangedTicks":0,"UnchangedVolume":0,"UpTicks":51048,"UpVolume":7269070,"OpenInterest":0},"Wed Feb 28 2018 21:00:00 GMT+0000 (Coordinated Universal Time)":{"Close":16.16,"DownTicks":71208,"DownVolume":10334225,"High":17.03,"Low":14.3,"Open":16.46,"Status":29,"TimeStamp":"/Date(1519851600000)/","TotalTicks":143684,"TotalVolume":20666111,"UnchangedTicks":0,"UnchangedVolume":0,"UpTicks":72476,"UpVolume":10331877,"OpenInterest":0},"Wed Jan 31 2018 21:00:00 GMT+0000 (Coordinated Universal Time)":{"Close":16.49,"DownTicks":61041,"DownVolume":8960186,"High":17.67,"Low":15.61,"Open":15.73,"Status":29,"TimeStamp":"/Date(1517432400000)/","TotalTicks":121496,"TotalVolume":18961715,"UnchangedTicks":0,"UnchangedVolume":0,"UpTicks":60455,"UpVolume":10001519,"OpenInterest":0},"Fri Dec 29 2017 21:00:00 GMT+0000 (Coordinated Universal Time)":{"Close":15.67,"DownTicks":66103,"DownVolume":10948620,"High":16.73,"Low":15.29,"Open":16.35,"Status":29,"TimeStamp":"/Date(1514581200000)/","TotalTicks":131958,"TotalVolume":20383171,"UnchangedTicks":0,"UnchangedVolume":0,"UpTicks":65855,"UpVolume":9434536,"OpenInterest":0},"Thu Nov 30 2017 21:00:00 GMT+0000 (Coordinated Universal Time)":{"Close":16.33,"DownTicks":76546,"DownVolume":10685919,"High":17.65,"Low":15.64,"Open":15.97,"Status":29,"TimeStamp":"/Date(1512075600000)/","TotalTicks":154707,"TotalVolume":22619206,"UnchangedTicks":0,"UnchangedVolume":0,"UpTicks":78161,"UpVolume":11933272,"OpenInterest":0},"Tue Oct 31 2017 20:00:00 GMT+0000 (Coordinated Universal Time)":{"Close":15.78,"DownTicks":62117,"DownVolume":9801908,"High":15.91,"Low":15.15,"Open":15.45,"Status":29,"TimeStamp":"/Date(1509480000000)/","TotalTicks":122705,"TotalVolume":19331498,"UnchangedTicks":0,"UnchangedVolume":0,"UpTicks":60588,"UpVolume":9529575,"OpenInterest":0},"Fri Sep 29 2017 20:00:00 GMT+0000 (Coordinated Universal Time)":{"Close":15.37,"DownTicks":79990,"DownVolume":12178432,"High":15.61,"Low":14.16,"Open":14.25,"Status":29,"TimeStamp":"/Date(1506715200000)/","TotalTicks":161381,"TotalVolume":25723183,"UnchangedTicks":0,"UnchangedVolume":0,"UpTicks":81391,"UpVolume":13544739,"OpenInterest":0},"Thu Aug 31 2017 20:00:00 GMT+0000 (Coordinated Universal Time)":{"Close":14.24,"DownTicks":137954,"DownVolume":26187186,"High":17.79,"Low":12.76,"Open":17.57,"Status":29,"TimeStamp":"/Date(1504209600000)/","TotalTicks":284985,"TotalVolume":52968065,"UnchangedTicks":0,"UnchangedVolume":0,"UpTicks":147031,"UpVolume":26780865,"OpenInterest":0},"Mon Jul 31 2017 20:00:00 GMT+0000 (Coordinated Universal Time)":{"Close":17.38,"DownTicks":61443,"DownVolume":10718783,"High":19.54,"Low":16.84,"Open":17.46,"Status":29,"TimeStamp":"/Date(1501531200000)/","TotalTicks":123055,"TotalVolume":21858663,"UnchangedTicks":0,"UnchangedVolume":0,"UpTicks":61612,"UpVolume":11139866,"OpenInterest":0},"Fri Jun 30 2017 20:00:00 GMT+0000 (Coordinated Universal Time)":{"Close":17.36,"DownTicks":95880,"DownVolume":14013148,"High":18.85,"Low":16.02,"Open":16.3,"Status":29,"TimeStamp":"/Date(1498852800000)/","TotalTicks":191165,"TotalVolume":29283735,"UnchangedTicks":0,"UnchangedVolume":0,"UpTicks":95285,"UpVolume":15270576,"OpenInterest":0}},"rsiData":{"Wed Jun 30 2021 20:00:00 GMT+0000 (Coordinated Universal Time)":54.43,"Mon May 31 2021 20:00:00 GMT+0000 (Coordinated Universal Time)":58.29,"Fri Apr 30 2021 20:00:00 GMT+0000 (Coordinated Universal Time)":59.82,"Wed Mar 31 2021 20:00:00 GMT+0000 (Coordinated Universal Time)":57.82,"Fri Feb 26 2021 21:00:00 GMT+0000 (Coordinated Universal Time)":56.53,"Fri Jan 29 2021 21:00:00 GMT+0000 (Coordinated Universal Time)":54.09,"Thu Dec 31 2020 21:00:00 GMT+0000 (Coordinated Universal Time)":55.68,"Mon Nov 30 2020 21:00:00 GMT+0000 (Coordinated Universal Time)":53.26,"Fri Oct 30 2020 20:00:00 GMT+0000 (Coordinated Universal Time)":49.09,"Wed Sep 30 2020 20:00:00 GMT+0000 (Coordinated Universal Time)":47.41,"Mon Aug 31 2020 20:00:00 GMT+0000 (Coordinated Universal Time)":47.57,"Fri Jul 31 2020 20:00:00 GMT+0000 (Coordinated Universal Time)":50.22,"Tue Jun 30 2020 20:00:00 GMT+0000 (Coordinated Universal Time)":48.82,"Fri May 29 2020 20:00:00 GMT+0000 (Coordinated Universal Time)":47.94,"Thu Apr 30 2020 20:00:00 GMT+0000 (Coordinated Universal Time)":47.99,"Tue Mar 31 2020 20:00:00 GMT+0000 (Coordinated Universal Time)":44.44,"Fri Feb 28 2020 21:00:00 GMT+0000 (Coordinated Universal Time)":51.33,"Fri Jan 31 2020 21:00:00 GMT+0000 (Coordinated Universal Time)":55.56,"Tue Dec 31 2019 21:00:00 GMT+0000 (Coordinated Universal Time)":57.64,"Fri Nov 29 2019 21:00:00 GMT+0000 (Coordinated Universal Time)":53.64,"Thu Oct 31 2019 20:00:00 GMT+0000 (Coordinated Universal Time)":49.01,"Mon Sep 30 2019 20:00:00 GMT+0000 (Coordinated Universal Time)":50.35,"Fri Aug 30 2019 20:00:00 GMT+0000 (Coordinated Universal Time)":46.02,"Wed Jul 31 2019 20:00:00 GMT+0000 (Coordinated Universal Time)":45.45,"Fri Jun 28 2019 20:00:00 GMT+0000 (Coordinated Universal Time)":44.74,"Fri May 31 2019 20:00:00 GMT+0000 (Coordinated Universal Time)":40.1,"Tue Apr 30 2019 20:00:00 GMT+0000 (Coordinated Universal Time)":51.41,"Fri Mar 29 2019 20:00:00 GMT+0000 (Coordinated Universal Time)":46.95,"Thu Feb 28 2019 21:00:00 GMT+0000 (Coordinated Universal Time)":48.01,"Thu Jan 31 2019 21:00:00 GMT+0000 (Coordinated Universal Time)":46.17,"Mon Dec 31 2018 21:00:00 GMT+0000 (Coordinated Universal Time)":40.84,"Fri Nov 30 2018 21:00:00 GMT+0000 (Coordinated Universal Time)":46.06,"Wed Oct 31 2018 20:00:00 GMT+0000 (Coordinated Universal Time)":45.49,"Fri Sep 28 2018 20:00:00 GMT+0000 (Coordinated Universal Time)":58.13,"Fri Aug 31 2018 20:00:00 GMT+0000 (Coordinated Universal Time)":70.11,"Tue Jul 31 2018 20:00:00 GMT+0000 (Coordinated Universal Time)":67.08,"Fri Jun 29 2018 20:00:00 GMT+0000 (Coordinated Universal Time)":68.38,"Thu May 31 2018 20:00:00 GMT+0000 (Coordinated Universal Time)":70.24,"Mon Apr 30 2018 20:00:00 GMT+0000 (Coordinated Universal Time)":59.84,"Fri Mar 30 2018 20:00:00 GMT+0000 (Coordinated Universal Time)":67.02,"Wed Feb 28 2018 21:00:00 GMT+0000 (Coordinated Universal Time)":72.21,"Wed Jan 31 2018 21:00:00 GMT+0000 (Coordinated Universal Time)":74.23,"Fri Dec 29 2017 21:00:00 GMT+0000 (Coordinated Universal Time)":72.45,"Thu Nov 30 2017 21:00:00 GMT+0000 (Coordinated Universal Time)":76.4,"Tue Oct 31 2017 20:00:00 GMT+0000 (Coordinated Universal Time)":75.36,"Fri Sep 29 2017 20:00:00 GMT+0000 (Coordinated Universal Time)":74.58,"Thu Aug 31 2017 20:00:00 GMT+0000 (Coordinated Universal Time)":72.36,"Mon Jul 31 2017 20:00:00 GMT+0000 (Coordinated Universal Time)":93.44,"Fri Jun 30 2017 20:00:00 GMT+0000 (Coordinated Universal Time)":93.43}}