{"priceData":{"Wed Jun 30 2021 20:00:00 GMT+0000 (Coordinated Universal Time)":{"Close":67.4,"DownTicks":59170,"DownVolume":3599358,"High":68.94,"Low":53.42,"Open":56.5,"Status":536870917,"TimeStamp":"/Date(1625083200000)/","TotalTicks":118079,"TotalVolume":7698213,"UnchangedTicks":0,"UnchangedVolume":0,"UpTicks":58909,"UpVolume":4098851,"OpenInterest":0},"Mon May 31 2021 20:00:00 GMT+0000 (Coordinated Universal Time)":{"Close":56.5,"DownTicks":68393,"DownVolume":4391650,"High":63.58,"Low":46.15,"Open":63.48,"Status":536870917,"TimeStamp":"/Date(1622491200000)/","TotalTicks":136976,"TotalVolume":8968735,"UnchangedTicks":0,"UnchangedVolume":0,"UpTicks":68583,"UpVolume":4577073,"OpenInterest":0},"Fri Apr 30 2021 20:00:00 GMT+0000 (Coordinated Universal Time)":{"Close":54.27,"DownTicks":9113,"DownVolume":708825,"High":56.74,"Low":52.8,"Open":56.6,"Status":536870917,"TimeStamp":"/Date(1619812800000)/","TotalTicks":18299,"TotalVolume":1425380,"UnchangedTicks":0,"UnchangedVolume":0,"UpTicks":9186,"UpVolume":716554,"OpenInterest":0},"Wed Mar 31 2021 20:00:00 GMT+0000 (Coordinated Universal Time)":{"Close":55.55,"DownTicks":138537,"DownVolume":15198071,"High":60,"Low":39.06,"Open":49.42,"Status":29,"TimeStamp":"/Date(1617220800000)/","TotalTicks":277391,"TotalVolume":32018685,"UnchangedTicks":0,"UnchangedVolume":0,"UpTicks":138854,"UpVolume":16820601,"OpenInterest":0},"Fri Feb 26 2021 21:00:00 GMT+0000 (Coordinated Universal Time)":{"Close":48.28,"DownTicks":70576,"DownVolume":6024825,"High":53.98,"Low":40.77,"Open":41.98,"Status":29,"TimeStamp":"/Date(1614373200000)/","TotalTicks":140610,"TotalVolume":12037325,"UnchangedTicks":0,"UnchangedVolume":0,"UpTicks":70034,"UpVolume":6012488,"OpenInterest":0},"Fri Jan 29 2021 21:00:00 GMT+0000 (Coordinated Universal Time)":{"Close":41.27,"DownTicks":64505,"DownVolume":7364180,"High":43.98,"Low":30.03,"Open":30.8,"Status":29,"TimeStamp":"/Date(1611954000000)/","TotalTicks":131969,"TotalVolume":14127059,"UnchangedTicks":0,"UnchangedVolume":0,"UpTicks":67464,"UpVolume":6762864,"OpenInterest":0},"Thu Dec 31 2020 21:00:00 GMT+0000 (Coordinated Universal Time)":{"Close":30.88,"DownTicks":52256,"DownVolume":7928259,"High":32,"Low":24.31,"Open":25.86,"Status":29,"TimeStamp":"/Date(1609448400000)/","TotalTicks":105446,"TotalVolume":13773264,"UnchangedTicks":0,"UnchangedVolume":0,"UpTicks":53190,"UpVolume":5844996,"OpenInterest":0},"Mon Nov 30 2020 21:00:00 GMT+0000 (Coordinated Universal Time)":{"Close":25.54,"DownTicks":54708,"DownVolume":5545861,"High":26.22,"Low":18.68,"Open":18.78,"Status":29,"TimeStamp":"/Date(1606770000000)/","TotalTicks":109445,"TotalVolume":10770200,"UnchangedTicks":0,"UnchangedVolume":0,"UpTicks":54737,"UpVolume":5224333,"OpenInterest":0},"Fri Oct 30 2020 20:00:00 GMT+0000 (Coordinated Universal Time)":{"Close":18.53,"DownTicks":47387,"DownVolume":5075064,"High":22.26,"Low":18.09,"Open":18.53,"Status":29,"TimeStamp":"/Date(1604088000000)/","TotalTicks":94499,"TotalVolume":10241350,"UnchangedTicks":0,"UnchangedVolume":0,"UpTicks":47112,"UpVolume":5166275,"OpenInterest":0},"Wed Sep 30 2020 20:00:00 GMT+0000 (Coordinated Universal Time)":{"Close":18.53,"DownTicks":55202,"DownVolume":6383639,"High":19.64,"Low":14.84,"Open":15.81,"Status":29,"TimeStamp":"/Date(1601496000000)/","TotalTicks":110614,"TotalVolume":12543250,"UnchangedTicks":0,"UnchangedVolume":0,"UpTicks":55412,"UpVolume":6159602,"OpenInterest":0},"Mon Aug 31 2020 20:00:00 GMT+0000 (Coordinated Universal Time)":{"Close":15.85,"DownTicks":48809,"DownVolume":4802821,"High":17.38,"Low":14.45,"Open":16.56,"Status":29,"TimeStamp":"/Date(1598904000000)/","TotalTicks":97815,"TotalVolume":9299637,"UnchangedTicks":0,"UnchangedVolume":0,"UpTicks":49006,"UpVolume":4496804,"OpenInterest":0},"Fri Jul 31 2020 20:00:00 GMT+0000 (Coordinated Universal Time)":{"Close":16.49,"DownTicks":52635,"DownVolume":6563951,"High":16.95,"Low":13.91,"Open":13.91,"Status":29,"TimeStamp":"/Date(1596225600000)/","TotalTicks":104270,"TotalVolume":12135633,"UnchangedTicks":0,"UnchangedVolume":0,"UpTicks":51635,"UpVolume":5571673,"OpenInterest":0},"Tue Jun 30 2020 20:00:00 GMT+0000 (Coordinated Universal Time)":{"Close":13.82,"DownTicks":59771,"DownVolume":7988335,"High":15.18,"Low":12.82,"Open":14.4,"Status":29,"TimeStamp":"/Date(1593547200000)/","TotalTicks":117629,"TotalVolume":14028901,"UnchangedTicks":0,"UnchangedVolume":0,"UpTicks":57858,"UpVolume":6040556,"OpenInterest":0},"Fri May 29 2020 20:00:00 GMT+0000 (Coordinated Universal Time)":{"Close":14.38,"DownTicks":60059,"DownVolume":7574731,"High":15.95,"Low":13.31,"Open":14.13,"Status":29,"TimeStamp":"/Date(1590782400000)/","TotalTicks":117944,"TotalVolume":14561288,"UnchangedTicks":0,"UnchangedVolume":0,"UpTicks":57885,"UpVolume":6986546,"OpenInterest":0},"Thu Apr 30 2020 20:00:00 GMT+0000 (Coordinated Universal Time)":{"Close":14.5,"DownTicks":62457,"DownVolume":7582681,"High":15,"Low":7.81,"Open":8.87,"Status":29,"TimeStamp":"/Date(1588276800000)/","TotalTicks":125783,"TotalVolume":16401555,"UnchangedTicks":0,"UnchangedVolume":0,"UpTicks":63326,"UpVolume":8818864,"OpenInterest":0},"Tue Mar 31 2020 20:00:00 GMT+0000 (Coordinated Universal Time)":{"Close":9.17,"DownTicks":83340,"DownVolume":9979015,"High":15.77,"Low":6.78,"Open":15.56,"Status":29,"TimeStamp":"/Date(1585684800000)/","TotalTicks":167216,"TotalVolume":20249020,"UnchangedTicks":0,"UnchangedVolume":0,"UpTicks":83876,"UpVolume":10269994,"OpenInterest":0},"Fri Feb 28 2020 21:00:00 GMT+0000 (Coordinated Universal Time)":{"Close":15.44,"DownTicks":54836,"DownVolume":5947532,"High":19.48,"Low":14.4,"Open":16.69,"Status":29,"TimeStamp":"/Date(1582923600000)/","TotalTicks":111392,"TotalVolume":12014322,"UnchangedTicks":0,"UnchangedVolume":0,"UpTicks":56556,"UpVolume":6066780,"OpenInterest":0},"Fri Jan 31 2020 21:00:00 GMT+0000 (Coordinated Universal Time)":{"Close":16.4,"DownTicks":56815,"DownVolume":6808829,"High":17.79,"Low":15.9,"Open":17.5,"Status":29,"TimeStamp":"/Date(1580504400000)/","TotalTicks":111511,"TotalVolume":13669708,"UnchangedTicks":0,"UnchangedVolume":0,"UpTicks":54696,"UpVolume":6860866,"OpenInterest":0},"Tue Dec 31 2019 21:00:00 GMT+0000 (Coordinated Universal Time)":{"Close":17.4,"DownTicks":41686,"DownVolume":4417528,"High":19.1,"Low":17.02,"Open":18.78,"Status":29,"TimeStamp":"/Date(1577826000000)/","TotalTicks":84027,"TotalVolume":9778628,"UnchangedTicks":0,"UnchangedVolume":0,"UpTicks":42341,"UpVolume":5361087,"OpenInterest":0},"Fri Nov 29 2019 21:00:00 GMT+0000 (Coordinated Universal Time)":{"Close":18.66,"DownTicks":47215,"DownVolume":5415416,"High":19.57,"Low":15.89,"Open":15.94,"Status":29,"TimeStamp":"/Date(1575061200000)/","TotalTicks":94694,"TotalVolume":10707147,"UnchangedTicks":0,"UnchangedVolume":0,"UpTicks":47479,"UpVolume":5291722,"OpenInterest":0},"Thu Oct 31 2019 20:00:00 GMT+0000 (Coordinated Universal Time)":{"Close":15.87,"DownTicks":42656,"DownVolume":4832499,"High":16.39,"Low":13.4,"Open":15.26,"Status":29,"TimeStamp":"/Date(1572552000000)/","TotalTicks":87143,"TotalVolume":9690328,"UnchangedTicks":0,"UnchangedVolume":0,"UpTicks":44487,"UpVolume":4857815,"OpenInterest":0},"Mon Sep 30 2019 20:00:00 GMT+0000 (Coordinated Universal Time)":{"Close":15.14,"DownTicks":43833,"DownVolume":4402398,"High":17,"Low":14.9,"Open":16.43,"Status":29,"TimeStamp":"/Date(1569873600000)/","TotalTicks":88049,"TotalVolume":9013913,"UnchangedTicks":0,"UnchangedVolume":0,"UpTicks":44216,"UpVolume":4611503,"OpenInterest":0},"Fri Aug 30 2019 20:00:00 GMT+0000 (Coordinated Universal Time)":{"Close":16.54,"DownTicks":51084,"DownVolume":5918482,"High":19.78,"Low":15.24,"Open":19.21,"Status":29,"TimeStamp":"/Date(1567195200000)/","TotalTicks":103761,"TotalVolume":11815634,"UnchangedTicks":0,"UnchangedVolume":0,"UpTicks":52677,"UpVolume":5897144,"OpenInterest":0},"Wed Jul 31 2019 20:00:00 GMT+0000 (Coordinated Universal Time)":{"Close":19.12,"DownTicks":36883,"DownVolume":3723098,"High":19.95,"Low":17.96,"Open":19.03,"Status":29,"TimeStamp":"/Date(1564603200000)/","TotalTicks":74012,"TotalVolume":7607632,"UnchangedTicks":0,"UnchangedVolume":0,"UpTicks":37129,"UpVolume":3884522,"OpenInterest":0},"Fri Jun 28 2019 20:00:00 GMT+0000 (Coordinated Universal Time)":{"Close":18.89,"DownTicks":45991,"DownVolume":5684585,"High":19,"Low":14.91,"Open":15.7,"Status":29,"TimeStamp":"/Date(1561752000000)/","TotalTicks":93858,"TotalVolume":11653806,"UnchangedTicks":0,"UnchangedVolume":0,"UpTicks":47867,"UpVolume":5969212,"OpenInterest":0},"Fri May 31 2019 20:00:00 GMT+0000 (Coordinated Universal Time)":{"Close":15.65,"DownTicks":53173,"DownVolume":7326005,"High":18.41,"Low":15.13,"Open":17.06,"Status":29,"TimeStamp":"/Date(1559332800000)/","TotalTicks":109677,"TotalVolume":13962984,"UnchangedTicks":0,"UnchangedVolume":0,"UpTicks":56504,"UpVolume":6636968,"OpenInterest":0},"Tue Apr 30 2019 20:00:00 GMT+0000 (Coordinated Universal Time)":{"Close":16.99,"DownTicks":47632,"DownVolume":5963822,"High":18.89,"Low":16.15,"Open":17.52,"Status":29,"TimeStamp":"/Date(1556654400000)/","TotalTicks":95097,"TotalVolume":11458420,"UnchangedTicks":0,"UnchangedVolume":0,"UpTicks":47465,"UpVolume":5494586,"OpenInterest":0},"Fri Mar 29 2019 20:00:00 GMT+0000 (Coordinated Universal Time)":{"Close":17.51,"DownTicks":48511,"DownVolume":6484782,"High":20.5,"Low":16.93,"Open":18.87,"Status":29,"TimeStamp":"/Date(1553889600000)/","TotalTicks":97357,"TotalVolume":12917241,"UnchangedTicks":0,"UnchangedVolume":0,"UpTicks":48846,"UpVolume":6432447,"OpenInterest":0},"Thu Feb 28 2019 21:00:00 GMT+0000 (Coordinated Universal Time)":{"Close":18.71,"DownTicks":50267,"DownVolume":7720706,"High":21.01,"Low":16.2,"Open":17.21,"Status":29,"TimeStamp":"/Date(1551387600000)/","TotalTicks":102143,"TotalVolume":14805407,"UnchangedTicks":0,"UnchangedVolume":0,"UpTicks":51876,"UpVolume":7084691,"OpenInterest":0},"Thu Jan 31 2019 21:00:00 GMT+0000 (Coordinated Universal Time)":{"Close":17.2,"DownTicks":41016,"DownVolume":5944110,"High":18.65,"Low":16.04,"Open":17.03,"Status":29,"TimeStamp":"/Date(1548968400000)/","TotalTicks":82134,"TotalVolume":13362231,"UnchangedTicks":0,"UnchangedVolume":0,"UpTicks":41118,"UpVolume":7418110,"OpenInterest":0},"Mon Dec 31 2018 21:00:00 GMT+0000 (Coordinated Universal Time)":{"Close":17.4,"DownTicks":47036,"DownVolume":9074942,"High":18.87,"Low":14,"Open":17.9,"Status":29,"TimeStamp":"/Date(1546290000000)/","TotalTicks":94847,"TotalVolume":16603224,"UnchangedTicks":0,"UnchangedVolume":0,"UpTicks":47811,"UpVolume":7528272,"OpenInterest":0},"Fri Nov 30 2018 21:00:00 GMT+0000 (Coordinated Universal Time)":{"Close":17.58,"DownTicks":84547,"DownVolume":14313994,"High":17.9,"Low":11.13,"Open":11.26,"Status":29,"TimeStamp":"/Date(1543611600000)/","TotalTicks":168782,"TotalVolume":29605603,"UnchangedTicks":0,"UnchangedVolume":0,"UpTicks":84235,"UpVolume":15291599,"OpenInterest":0},"Wed Oct 31 2018 20:00:00 GMT+0000 (Coordinated Universal Time)":{"Close":11.15,"DownTicks":59814,"DownVolume":10352371,"High":15.29,"Low":10.51,"Open":14.23,"Status":29,"TimeStamp":"/Date(1541016000000)/","TotalTicks":117529,"TotalVolume":19913314,"UnchangedTicks":0,"UnchangedVolume":0,"UpTicks":57715,"UpVolume":9560931,"OpenInterest":0},"Fri Sep 28 2018 20:00:00 GMT+0000 (Coordinated Universal Time)":{"Close":14.15,"DownTicks":49148,"DownVolume":9567440,"High":14.95,"Low":11.45,"Open":12.15,"Status":29,"TimeStamp":"/Date(1538164800000)/","TotalTicks":99891,"TotalVolume":18346365,"UnchangedTicks":0,"UnchangedVolume":0,"UpTicks":50743,"UpVolume":8778914,"OpenInterest":0},"Fri Aug 31 2018 20:00:00 GMT+0000 (Coordinated Universal Time)":{"Close":12.2,"DownTicks":53093,"DownVolume":9512378,"High":13.2,"Low":9.7,"Open":10.5,"Status":29,"TimeStamp":"/Date(1535745600000)/","TotalTicks":105942,"TotalVolume":19520161,"UnchangedTicks":0,"UnchangedVolume":0,"UpTicks":52849,"UpVolume":10007773,"OpenInterest":0},"Tue Jul 31 2018 20:00:00 GMT+0000 (Coordinated Universal Time)":{"Close":10.45,"DownTicks":49970,"DownVolume":11229823,"High":10.95,"Low":8.95,"Open":9.45,"Status":29,"TimeStamp":"/Date(1533067200000)/","TotalTicks":103108,"TotalVolume":21214563,"UnchangedTicks":0,"UnchangedVolume":0,"UpTicks":53138,"UpVolume":9984724,"OpenInterest":0},"Fri Jun 29 2018 20:00:00 GMT+0000 (Coordinated Universal Time)":{"Close":9.7,"DownTicks":73389,"DownVolume":21098678,"High":14.65,"Low":9.25,"Open":13.45,"Status":29,"TimeStamp":"/Date(1530302400000)/","TotalTicks":147248,"TotalVolume":39757254,"UnchangedTicks":0,"UnchangedVolume":0,"UpTicks":73859,"UpVolume":18658570,"OpenInterest":0},"Thu May 31 2018 20:00:00 GMT+0000 (Coordinated Universal Time)":{"Close":13.45,"DownTicks":47893,"DownVolume":9040422,"High":14.75,"Low":11,"Open":13.45,"Status":29,"TimeStamp":"/Date(1527796800000)/","TotalTicks":92812,"TotalVolume":17660329,"UnchangedTicks":0,"UnchangedVolume":0,"UpTicks":44919,"UpVolume":8619899,"OpenInterest":0},"Mon Apr 30 2018 20:00:00 GMT+0000 (Coordinated Universal Time)":{"Close":13.35,"DownTicks":50407,"DownVolume":9990038,"High":13.59,"Low":9.25,"Open":10,"Status":29,"TimeStamp":"/Date(1525118400000)/","TotalTicks":100677,"TotalVolume":20143944,"UnchangedTicks":0,"UnchangedVolume":0,"UpTicks":50270,"UpVolume":10153898,"OpenInterest":0},"Fri Mar 30 2018 20:00:00 GMT+0000 (Coordinated Universal Time)":{"Close":9.95,"DownTicks":75439,"DownVolume":16713594,"High":12.8,"Low":7.9,"Open":7.95,"Status":13,"TimeStamp":"/Date(1522440000000)/","TotalTicks":146365,"TotalVolume":32115007,"UnchangedTicks":0,"UnchangedVolume":0,"UpTicks":70926,"UpVolume":15401400,"OpenInterest":0},"Wed Feb 28 2018 21:00:00 GMT+0000 (Coordinated Universal Time)":{"Close":8,"DownTicks":28310,"DownVolume":7302992,"High":8.5,"Low":6,"Open":7.75,"Status":29,"TimeStamp":"/Date(1519851600000)/","TotalTicks":55486,"TotalVolume":13791702,"UnchangedTicks":0,"UnchangedVolume":0,"UpTicks":27176,"UpVolume":6488698,"OpenInterest":0},"Wed Jan 31 2018 21:00:00 GMT+0000 (Coordinated Universal Time)":{"Close":7.7,"DownTicks":29356,"DownVolume":9473435,"High":7.75,"Low":5.33,"Open":5.6,"Status":29,"TimeStamp":"/Date(1517432400000)/","TotalTicks":56234,"TotalVolume":17535612,"UnchangedTicks":0,"UnchangedVolume":0,"UpTicks":26878,"UpVolume":8062173,"OpenInterest":0},"Fri Dec 29 2017 21:00:00 GMT+0000 (Coordinated Universal Time)":{"Close":5.45,"DownTicks":16398,"DownVolume":5459073,"High":5.6,"Low":4.4,"Open":4.55,"Status":29,"TimeStamp":"/Date(1514581200000)/","TotalTicks":31789,"TotalVolume":10106592,"UnchangedTicks":0,"UnchangedVolume":0,"UpTicks":15391,"UpVolume":4647512,"OpenInterest":0},"Thu Nov 30 2017 21:00:00 GMT+0000 (Coordinated Universal Time)":{"Close":4.45,"DownTicks":15605,"DownVolume":5090432,"High":4.7,"Low":3.3,"Open":4.5,"Status":29,"TimeStamp":"/Date(1512075600000)/","TotalTicks":31431,"TotalVolume":10033011,"UnchangedTicks":0,"UnchangedVolume":0,"UpTicks":15826,"UpVolume":4942572,"OpenInterest":0},"Tue Oct 31 2017 20:00:00 GMT+0000 (Coordinated Universal Time)":{"Close":4.55,"DownTicks":31764,"DownVolume":10421235,"High":6.15,"Low":4.15,"Open":6.05,"Status":29,"TimeStamp":"/Date(1509480000000)/","TotalTicks":63361,"TotalVolume":19843785,"UnchangedTicks":0,"UnchangedVolume":0,"UpTicks":31597,"UpVolume":9422537,"OpenInterest":0},"Fri Sep 29 2017 20:00:00 GMT+0000 (Coordinated Universal Time)":{"Close":6,"DownTicks":22505,"DownVolume":7937082,"High":6.3,"Low":4.05,"Open":4.35,"Status":29,"TimeStamp":"/Date(1506715200000)/","TotalTicks":43478,"TotalVolume":14669818,"UnchangedTicks":0,"UnchangedVolume":0,"UpTicks":20973,"UpVolume":6732729,"OpenInterest":0},"Thu Aug 31 2017 20:00:00 GMT+0000 (Coordinated Universal Time)":{"Close":4.3,"DownTicks":20934,"DownVolume":7724008,"High":4.7,"Low":3,"Open":3.25,"Status":29,"TimeStamp":"/Date(1504209600000)/","TotalTicks":39175,"TotalVolume":14432433,"UnchangedTicks":0,"UnchangedVolume":0,"UpTicks":18241,"UpVolume":6708416,"OpenInterest":0},"Mon Jul 31 2017 20:00:00 GMT+0000 (Coordinated Universal Time)":{"Close":3.25,"DownTicks":8679,"DownVolume":3280053,"High":3.55,"Low":3,"Open":3.25,"Status":29,"TimeStamp":"/Date(1501531200000)/","TotalTicks":17495,"TotalVolume":6782881,"UnchangedTicks":0,"UnchangedVolume":0,"UpTicks":8816,"UpVolume":3502819,"OpenInterest":0},"Fri Jun 30 2017 20:00:00 GMT+0000 (Coordinated Universal Time)":{"Close":3.3,"DownTicks":10699,"DownVolume":4561404,"High":3.6,"Low":2.55,"Open":3,"Status":29,"TimeStamp":"/Date(1498852800000)/","TotalTicks":20914,"TotalVolume":8884297,"UnchangedTicks":0,"UnchangedVolume":0,"UpTicks":10215,"UpVolume":4322883,"OpenInterest":0}},"rsiData":{"Wed Jun 30 2021 20:00:00 GMT+0000 (Coordinated Universal Time)":87.55,"Mon May 31 2021 20:00:00 GMT+0000 (Coordinated Universal Time)":84.36,"Fri Apr 30 2021 20:00:00 GMT+0000 (Coordinated Universal Time)":83.54,"Wed Mar 31 2021 20:00:00 GMT+0000 (Coordinated Universal Time)":85.9,"Fri Feb 26 2021 21:00:00 GMT+0000 (Coordinated Universal Time)":83.43,"Fri Jan 29 2021 21:00:00 GMT+0000 (Coordinated Universal Time)":80.35,"Thu Dec 31 2020 21:00:00 GMT+0000 (Coordinated Universal Time)":73.58,"Mon Nov 30 2020 21:00:00 GMT+0000 (Coordinated Universal Time)":68.39,"Fri Oct 30 2020 20:00:00 GMT+0000 (Coordinated Universal Time)":58.43,"Wed Sep 30 2020 20:00:00 GMT+0000 (Coordinated Universal Time)":58.43,"Mon Aug 31 2020 20:00:00 GMT+0000 (Coordinated Universal Time)":53.61,"Fri Jul 31 2020 20:00:00 GMT+0000 (Coordinated Universal Time)":55.02,"Tue Jun 30 2020 20:00:00 GMT+0000 (Coordinated Universal Time)":49.9,"Fri May 29 2020 20:00:00 GMT+0000 (Coordinated Universal Time)":51.04,"Thu Apr 30 2020 20:00:00 GMT+0000 (Coordinated Universal Time)":51.27,"Tue Mar 31 2020 20:00:00 GMT+0000 (Coordinated Universal Time)":40.06,"Fri Feb 28 2020 21:00:00 GMT+0000 (Coordinated Universal Time)":53.5,"Fri Jan 31 2020 21:00:00 GMT+0000 (Coordinated Universal Time)":56.18,"Tue Dec 31 2019 21:00:00 GMT+0000 (Coordinated Universal Time)":59.04,"Fri Nov 29 2019 21:00:00 GMT+0000 (Coordinated Universal Time)":62.77,"Thu Oct 31 2019 20:00:00 GMT+0000 (Coordinated Universal Time)":57.2,"Mon Sep 30 2019 20:00:00 GMT+0000 (Coordinated Universal Time)":55.59,"Fri Aug 30 2019 20:00:00 GMT+0000 (Coordinated Universal Time)":59.59,"Wed Jul 31 2019 20:00:00 GMT+0000 (Coordinated Universal Time)":67.97,"Fri Jun 28 2019 20:00:00 GMT+0000 (Coordinated Universal Time)":67.59,"Fri May 31 2019 20:00:00 GMT+0000 (Coordinated Universal Time)":61.69,"Tue Apr 30 2019 20:00:00 GMT+0000 (Coordinated Universal Time)":66.33,"Fri Mar 29 2019 20:00:00 GMT+0000 (Coordinated Universal Time)":68.18,"Thu Feb 28 2019 21:00:00 GMT+0000 (Coordinated Universal Time)":72.51,"Thu Jan 31 2019 21:00:00 GMT+0000 (Coordinated Universal Time)":70.31,"Mon Dec 31 2018 21:00:00 GMT+0000 (Coordinated Universal Time)":71,"Fri Nov 30 2018 21:00:00 GMT+0000 (Coordinated Universal Time)":71.6,"Wed Oct 31 2018 20:00:00 GMT+0000 (Coordinated Universal Time)":60.66,"Fri Sep 28 2018 20:00:00 GMT+0000 (Coordinated Universal Time)":72.81,"Fri Aug 31 2018 20:00:00 GMT+0000 (Coordinated Universal Time)":69.07,"Tue Jul 31 2018 20:00:00 GMT+0000 (Coordinated Universal Time)":65.07,"Fri Jun 29 2018 20:00:00 GMT+0000 (Coordinated Universal Time)":63.17,"Thu May 31 2018 20:00:00 GMT+0000 (Coordinated Universal Time)":84.48,"Mon Apr 30 2018 20:00:00 GMT+0000 (Coordinated Universal Time)":84.35,"Fri Mar 30 2018 20:00:00 GMT+0000 (Coordinated Universal Time)":78.68,"Wed Feb 28 2018 21:00:00 GMT+0000 (Coordinated Universal Time)":73.58,"Wed Jan 31 2018 21:00:00 GMT+0000 (Coordinated Universal Time)":72.64,"Fri Dec 29 2017 21:00:00 GMT+0000 (Coordinated Universal Time)":63.71,"Thu Nov 30 2017 21:00:00 GMT+0000 (Coordinated Universal Time)":58.05,"Tue Oct 31 2017 20:00:00 GMT+0000 (Coordinated Universal Time)":58.9,"Fri Sep 29 2017 20:00:00 GMT+0000 (Coordinated Universal Time)":73.42,"Thu Aug 31 2017 20:00:00 GMT+0000 (Coordinated Universal Time)":63.67,"Mon Jul 31 2017 20:00:00 GMT+0000 (Coordinated Universal Time)":54,"Fri Jun 30 2017 20:00:00 GMT+0000 (Coordinated Universal Time)":54.65}}