{"rsiData":{"Fri Apr 30 2021 20:00:00 GMT+0000 (Coordinated Universal Time)":45.89,"Fri Jan 29 2021 21:00:00 GMT+0000 (Coordinated Universal Time)":45.13,"Fri Oct 30 2020 20:00:00 GMT+0000 (Coordinated Universal Time)":42.84,"Fri Jul 31 2020 20:00:00 GMT+0000 (Coordinated Universal Time)":44.59,"Thu Apr 30 2020 20:00:00 GMT+0000 (Coordinated Universal Time)":43.63,"Fri Jan 31 2020 21:00:00 GMT+0000 (Coordinated Universal Time)":42.68,"Thu Oct 31 2019 20:00:00 GMT+0000 (Coordinated Universal Time)":55.12,"Wed Jul 31 2019 20:00:00 GMT+0000 (Coordinated Universal Time)":53.45,"Tue Apr 30 2019 20:00:00 GMT+0000 (Coordinated Universal Time)":53.07,"Thu Jan 31 2019 21:00:00 GMT+0000 (Coordinated Universal Time)":53.96,"Wed Oct 31 2018 20:00:00 GMT+0000 (Coordinated Universal Time)":52.25,"Tue Jul 31 2018 20:00:00 GMT+0000 (Coordinated Universal Time)":47.33,"Mon Apr 30 2018 20:00:00 GMT+0000 (Coordinated Universal Time)":54.46,"Wed Jan 31 2018 21:00:00 GMT+0000 (Coordinated Universal Time)":51.35,"Tue Oct 31 2017 20:00:00 GMT+0000 (Coordinated Universal Time)":53.12,"Mon Jul 31 2017 20:00:00 GMT+0000 (Coordinated Universal Time)":54.33,"Fri Apr 28 2017 20:00:00 GMT+0000 (Coordinated Universal Time)":44.91,"Tue Jan 31 2017 21:00:00 GMT+0000 (Coordinated Universal Time)":43.3,"Mon Oct 31 2016 20:00:00 GMT+0000 (Coordinated Universal Time)":44.61,"Fri Jul 29 2016 20:00:00 GMT+0000 (Coordinated Universal Time)":42.54,"Fri Apr 29 2016 20:00:00 GMT+0000 (Coordinated Universal Time)":45.18,"Fri Jan 29 2016 21:00:00 GMT+0000 (Coordinated Universal Time)":55.71,"Fri Oct 30 2015 20:00:00 GMT+0000 (Coordinated Universal Time)":52.3,"Fri Jul 31 2015 20:00:00 GMT+0000 (Coordinated Universal Time)":49.62,"Thu Apr 30 2015 20:00:00 GMT+0000 (Coordinated Universal Time)":52.22,"Fri Jan 30 2015 21:00:00 GMT+0000 (Coordinated Universal Time)":51.23,"Fri Oct 31 2014 20:00:00 GMT+0000 (Coordinated Universal Time)":53.96,"Thu Jul 31 2014 20:00:00 GMT+0000 (Coordinated Universal Time)":60.25,"Wed Apr 30 2014 20:00:00 GMT+0000 (Coordinated Universal Time)":82.79,"Fri Jan 31 2014 21:00:00 GMT+0000 (Coordinated Universal Time)":85.83,"Thu Oct 31 2013 20:00:00 GMT+0000 (Coordinated Universal Time)":84.97,"Wed Jul 31 2013 20:00:00 GMT+0000 (Coordinated Universal Time)":82.02,"Tue Apr 30 2013 20:00:00 GMT+0000 (Coordinated Universal Time)":81.32,"Thu Jan 31 2013 21:00:00 GMT+0000 (Coordinated Universal Time)":74.01,"Wed Oct 31 2012 20:00:00 GMT+0000 (Coordinated Universal Time)":75.49,"Tue Jul 31 2012 20:00:00 GMT+0000 (Coordinated Universal Time)":73.15,"Mon Apr 30 2012 20:00:00 GMT+0000 (Coordinated Universal Time)":72.42,"Tue Jan 31 2012 21:00:00 GMT+0000 (Coordinated Universal Time)":72.1,"Mon Oct 31 2011 20:00:00 GMT+0000 (Coordinated Universal Time)":65.37,"Fri Jul 29 2011 20:00:00 GMT+0000 (Coordinated Universal Time)":64.53,"Fri Apr 29 2011 20:00:00 GMT+0000 (Coordinated Universal Time)":63.7,"Mon Jan 31 2011 21:00:00 GMT+0000 (Coordinated Universal Time)":65.9,"Fri Oct 29 2010 20:00:00 GMT+0000 (Coordinated Universal Time)":63.37,"Fri Jul 30 2010 20:00:00 GMT+0000 (Coordinated Universal Time)":64.46,"Fri Apr 30 2010 20:00:00 GMT+0000 (Coordinated Universal Time)":58.47,"Fri Jan 29 2010 21:00:00 GMT+0000 (Coordinated Universal Time)":61.93,"Fri Oct 30 2009 20:00:00 GMT+0000 (Coordinated Universal Time)":58.75,"Fri Jul 31 2009 20:00:00 GMT+0000 (Coordinated Universal Time)":52.52,"Thu Apr 30 2009 20:00:00 GMT+0000 (Coordinated Universal Time)":52.04,"Fri Jan 30 2009 21:00:00 GMT+0000 (Coordinated Universal Time)":43.99,"Fri Oct 31 2008 20:00:00 GMT+0000 (Coordinated Universal Time)":51.85,"Thu Jul 31 2008 20:00:00 GMT+0000 (Coordinated Universal Time)":56.59,"Wed Apr 30 2008 20:00:00 GMT+0000 (Coordinated Universal Time)":63.05},"priceData":{"Fri Apr 30 2021 20:00:00 GMT+0000 (Coordinated Universal Time)":{"Open":14.8,"High":15.4,"Low":14.57,"Close":15.4},"Fri Jan 29 2021 21:00:00 GMT+0000 (Coordinated Universal Time)":{"Open":14.43,"High":15.74,"Low":13.69,"Close":15.15},"Fri Oct 30 2020 20:00:00 GMT+0000 (Coordinated Universal Time)":{"Open":15.15,"High":16.47,"Low":13.41,"Close":14.38},"Fri Jul 31 2020 20:00:00 GMT+0000 (Coordinated Universal Time)":{"Open":14.93,"High":17,"Low":13.18,"Close":15.16},"Thu Apr 30 2020 20:00:00 GMT+0000 (Coordinated Universal Time)":{"Open":13.55,"High":18.3,"Low":12.5,"Close":14.81},"Fri Jan 31 2020 21:00:00 GMT+0000 (Coordinated Universal Time)":{"Open":19.95,"High":20.7,"Low":10.65,"Close":14.45},"Thu Oct 31 2019 20:00:00 GMT+0000 (Coordinated Universal Time)":{"Open":19.08,"High":20.89,"Low":17.99,"Close":19.65},"Wed Jul 31 2019 20:00:00 GMT+0000 (Coordinated Universal Time)":{"Open":19.04,"High":20.5,"Low":17.74,"Close":18.96},"Tue Apr 30 2019 20:00:00 GMT+0000 (Coordinated Universal Time)":{"Open":19.15,"High":20.81,"Low":18.14,"Close":18.8},"Thu Jan 31 2019 21:00:00 GMT+0000 (Coordinated Universal Time)":{"Open":18.91,"High":20.75,"Low":18.09,"Close":19.15},"Wed Oct 31 2018 20:00:00 GMT+0000 (Coordinated Universal Time)":{"Open":16.35,"High":18.7,"Low":15.51,"Close":18.34},"Tue Jul 31 2018 20:00:00 GMT+0000 (Coordinated Universal Time)":{"Open":19.1,"High":19.8,"Low":16.05,"Close":16.15},"Mon Apr 30 2018 20:00:00 GMT+0000 (Coordinated Universal Time)":{"Open":17.6,"High":20.33,"Low":17.2,"Close":19.15},"Wed Jan 31 2018 21:00:00 GMT+0000 (Coordinated Universal Time)":{"Open":18.91,"High":19.7,"Low":16.11,"Close":17.78},"Tue Oct 31 2017 20:00:00 GMT+0000 (Coordinated Universal Time)":{"Open":18.4,"High":20.83,"Low":14.5,"Close":18.5},"Mon Jul 31 2017 20:00:00 GMT+0000 (Coordinated Universal Time)":{"Open":14.6,"High":20,"Low":14.5,"Close":19},"Fri Apr 28 2017 20:00:00 GMT+0000 (Coordinated Universal Time)":{"Open":14.2,"High":17.55,"Low":13.25,"Close":14.95},"Tue Jan 31 2017 21:00:00 GMT+0000 (Coordinated Universal Time)":{"Open":14.9,"High":15.75,"Low":14.1,"Close":14.35},"Mon Oct 31 2016 20:00:00 GMT+0000 (Coordinated Universal Time)":{"Open":14.1,"High":16.45,"Low":13.62,"Close":15},"Fri Jul 29 2016 20:00:00 GMT+0000 (Coordinated Universal Time)":{"Open":16.32,"High":16.47,"Low":13.02,"Close":14.17},"Fri Apr 29 2016 20:00:00 GMT+0000 (Coordinated Universal Time)":{"Open":20.25,"High":21.1,"Low":15.16,"Close":15.57},"Fri Jan 29 2016 21:00:00 GMT+0000 (Coordinated Universal Time)":{"Open":18.75,"High":22.99,"Low":17.9,"Close":20.17},"Fri Oct 30 2015 20:00:00 GMT+0000 (Coordinated Universal Time)":{"Open":18.43,"High":20.42,"Low":17.51,"Close":18.65},"Fri Jul 31 2015 20:00:00 GMT+0000 (Coordinated Universal Time)":{"Open":18.93,"High":20.5,"Low":17.4,"Close":17.52},"Thu Apr 30 2015 20:00:00 GMT+0000 (Coordinated Universal Time)":{"Open":18.01,"High":22.47,"Low":17.36,"Close":18.6},"Fri Jan 30 2015 21:00:00 GMT+0000 (Coordinated Universal Time)":{"Open":19.15,"High":22.05,"Low":17.05,"Close":18.15},"Fri Oct 31 2014 20:00:00 GMT+0000 (Coordinated Universal Time)":{"Open":21.62,"High":22.5,"Low":18.26,"Close":19.33},"Thu Jul 31 2014 20:00:00 GMT+0000 (Coordinated Universal Time)":{"Open":28.69,"High":31.08,"Low":19.5,"Close":21.83},"Wed Apr 30 2014 20:00:00 GMT+0000 (Coordinated Universal Time)":{"Open":28.68,"High":34.75,"Low":26.16,"Close":28.11},"Fri Jan 31 2014 21:00:00 GMT+0000 (Coordinated Universal Time)":{"Open":27.4,"High":29.08,"Low":26.1,"Close":28.75},"Thu Oct 31 2013 20:00:00 GMT+0000 (Coordinated Universal Time)":{"Open":24.66,"High":29.49,"Low":23.75,"Close":27.68},"Wed Jul 31 2013 20:00:00 GMT+0000 (Coordinated Universal Time)":{"Open":23.91,"High":27.94,"Low":23.3,"Close":24.55},"Tue Apr 30 2013 20:00:00 GMT+0000 (Coordinated Universal Time)":{"Open":19.11,"High":28.1,"Low":19.11,"Close":23.9},"Thu Jan 31 2013 21:00:00 GMT+0000 (Coordinated Universal Time)":{"Open":19.35,"High":22.25,"Low":18,"Close":18.9},"Wed Oct 31 2012 20:00:00 GMT+0000 (Coordinated Universal Time)":{"Open":17.62,"High":19.44,"Low":15.8,"Close":19.17},"Tue Jul 31 2012 20:00:00 GMT+0000 (Coordinated Universal Time)":{"Open":17.64,"High":19.01,"Low":15.75,"Close":17.9},"Mon Apr 30 2012 20:00:00 GMT+0000 (Coordinated Universal Time)":{"Open":17.58,"High":22.92,"Low":16.8,"Close":17.52},"Tue Jan 31 2012 21:00:00 GMT+0000 (Coordinated Universal Time)":{"Open":14.21,"High":17.52,"Low":13.91,"Close":17.35},"Mon Oct 31 2011 20:00:00 GMT+0000 (Coordinated Universal Time)":{"Open":13.95,"High":14.25,"Low":13.26,"Close":14.25},"Fri Jul 29 2011 20:00:00 GMT+0000 (Coordinated Universal Time)":{"Open":13.58,"High":14,"Low":11.5,"Close":13.92},"Fri Apr 29 2011 20:00:00 GMT+0000 (Coordinated Universal Time)":{"Open":13.88,"High":14.65,"Low":13,"Close":13.59},"Mon Jan 31 2011 21:00:00 GMT+0000 (Coordinated Universal Time)":{"Open":13,"High":14.35,"Low":13,"Close":14.1},"Fri Oct 29 2010 20:00:00 GMT+0000 (Coordinated Universal Time)":{"Open":13.24,"High":14.42,"Low":11.95,"Close":13},"Fri Jul 30 2010 20:00:00 GMT+0000 (Coordinated Universal Time)":{"Open":10.76,"High":13.5,"Low":9.99,"Close":13.27},"Fri Apr 30 2010 20:00:00 GMT+0000 (Coordinated Universal Time)":{"Open":11.55,"High":13.92,"Low":10.73,"Close":10.83},"Fri Jan 29 2010 21:00:00 GMT+0000 (Coordinated Universal Time)":{"Open":10.5,"High":13.02,"Low":10.26,"Close":11.7},"Fri Oct 30 2009 20:00:00 GMT+0000 (Coordinated Universal Time)":{"Open":8.58,"High":11.49,"Low":8.29,"Close":10.48},"Fri Jul 31 2009 20:00:00 GMT+0000 (Coordinated Universal Time)":{"Open":8.29,"High":9,"Low":7.56,"Close":8.41},"Thu Apr 30 2009 20:00:00 GMT+0000 (Coordinated Universal Time)":{"Open":6.01,"High":8.77,"Low":5.66,"Close":8.26},"Fri Jan 30 2009 21:00:00 GMT+0000 (Coordinated Universal Time)":{"Open":8.2,"High":10,"Low":4.4,"Close":6},"Fri Oct 31 2008 20:00:00 GMT+0000 (Coordinated Universal Time)":{"Open":9.21,"High":9.64,"Low":6.21,"Close":8.2},"Thu Jul 31 2008 20:00:00 GMT+0000 (Coordinated Universal Time)":{"Open":10.5,"High":11.25,"Low":8.76,"Close":9.31},"Wed Apr 30 2008 20:00:00 GMT+0000 (Coordinated Universal Time)":{"Open":9.4,"High":11.81,"Low":9.08,"Close":10.65}}}